gendisc/__init__.py
gendisc/__main__.py
gendisc/constants.py
gendisc/genlabel.py
gendisc/main.py
gendisc/py.typed
gendisc/templates/label.svg.j2
gendisc/templates/print-label.scm.j2
gendisc/templates/process.sh.j2
gendisc/utils.py
gendisc-0.0.14.dist-info/METADATA
gendisc-0.0.14.dist-info/WHEEL
gendisc-0.0.14.dist-info/entry_points.txt
gendisc-0.0.14.dist-info/licenses/LICENSE.txt
gendisc-0.0.14.dist-info/RECORD
