Metadata-Version: 2.4
Name: gendisc
Version: 0.0.14
Summary: Generate disk file path lists for mkisofs.
License-Expression: MIT
License-File: LICENSE.txt
Keywords: backup,iso,media,optical
Author: Andrew Udvare
Author-email: audvare@gmail.com
Requires-Python: >=3.10,<4.0
Classifier: Development Status :: 4 - Beta
Classifier: Intended Audience :: Developers
Classifier: Programming Language :: Python
Classifier: Programming Language :: Python :: 3.10
Classifier: Programming Language :: Python :: 3.11
Classifier: Programming Language :: Python :: 3.12
Classifier: Programming Language :: Python :: 3.13
Classifier: Programming Language :: Python :: 3.14
Classifier: Typing :: Typed
Requires-Dist: bascom (>=0.1.0,<0.2.0)
Requires-Dist: click (>=8.3.1,<9.0.0)
Requires-Dist: jinja2 (>=3.1.6,<4.0.0)
Requires-Dist: python-fsutil (>=0.15.0,<0.16.0)
Requires-Dist: tqdm (>=4.67.1,<5.0.0)
Requires-Dist: typing-extensions (>=4.15.0,<5.0.0)
Requires-Dist: wakepy (>=0.10.2.post1,<0.11.0)
Project-URL: Documentation, https://gendisc.readthedocs.org
Project-URL: Homepage, https://tatsh.github.io/gendisc/
Project-URL: Issues, https://github.com/Tatsh/gendisc/issues
Project-URL: Repository, https://github.com/Tatsh/gendisc
